MANIFEST.in
setup.py
src/ore/__init__.py
src/ore.extjs.egg-info/PKG-INFO
src/ore.extjs.egg-info/SOURCES.txt
src/ore.extjs.egg-info/dependency_links.txt
src/ore.extjs.egg-info/namespace_packages.txt
src/ore.extjs.egg-info/not-zip-safe
src/ore.extjs.egg-info/requires.txt
src/ore.extjs.egg-info/top_level.txt
src/ore/extjs/__init__.py
src/ore/extjs/configure.zcml
src/ore/extjs/getext.sh
src/ore/extjs/interfaces.py
src/ore/extjs/ext-2.0/CHANGES.txt
src/ore/extjs/ext-2.0/INCLUDE_ORDER.txt
src/ore/extjs/ext-2.0/LICENSE.txt
src/ore/extjs/ext-2.0/ext-all-debug.js
src/ore/extjs/ext-2.0/ext-all.js
src/ore/extjs/ext-2.0/ext-core-debug.js
src/ore/extjs/ext-2.0/ext-core.js
src/ore/extjs/ext-2.0/adapter/ext/ext-base.js
src/ore/extjs/ext-2.0/adapter/jquery/ext-jquery-adapter.js
src/ore/extjs/ext-2.0/adapter/jquery/jquery.js
src/ore/extjs/ext-2.0/adapter/prototype/effects.js
src/ore/extjs/ext-2.0/adapter/prototype/ext-prototype-adapter.js
src/ore/extjs/ext-2.0/adapter/prototype/prototype.js
src/ore/extjs/ext-2.0/adapter/prototype/scriptaculous.js
src/ore/extjs/ext-2.0/adapter/yui/ext-yui-adapter.js
src/ore/extjs/ext-2.0/adapter/yui/yui-utilities.js
src/ore/extjs/ext-2.0/resources/license.txt
src/ore/extjs/ext-2.0/resources/resources.jsb
src/ore/extjs/ext-2.0/resources/css/README.txt
src/ore/extjs/ext-2.0/resources/css/borders.css
src/ore/extjs/ext-2.0/resources/css/box.css
src/ore/extjs/ext-2.0/resources/css/button.css
src/ore/extjs/ext-2.0/resources/css/combo.css
src/ore/extjs/ext-2.0/resources/css/core.css
src/ore/extjs/ext-2.0/resources/css/date-picker.css
src/ore/extjs/ext-2.0/resources/css/dd.css
src/ore/extjs/ext-2.0/resources/css/debug.css
src/ore/extjs/ext-2.0/resources/css/dialog.css
src/ore/extjs/ext-2.0/resources/css/editor.css
src/ore/extjs/ext-2.0/resources/css/ext-all.css
src/ore/extjs/ext-2.0/resources/css/form.css
src/ore/extjs/ext-2.0/resources/css/grid.css
src/ore/extjs/ext-2.0/resources/css/layout.css
src/ore/extjs/ext-2.0/resources/css/menu.css
src/ore/extjs/ext-2.0/resources/css/panel.css
src/ore/extjs/ext-2.0/resources/css/progress.css
src/ore/extjs/ext-2.0/resources/css/qtips.css
src/ore/extjs/ext-2.0/resources/css/reset-min.css
src/ore/extjs/ext-2.0/resources/css/reset.css
