Metadata-Version: 1.0
Name: ore.extjs
Version: 2.0.2
Summary: Minimal ExtJS resource bundling in a Zope3 UI Layer
Home-page: UNKNOWN
Author: Kapil Thangavelu
Author-email: kapilt@gmail.com
License: UNKNOWN
Keywords: zope3
Platform: UNKNOWN
Classifier: Environment :: Web Environment
Classifier: Intended Audience :: Developers
Classifier: License :: OSI Approved :: Zope Public License
Classifier: Programming Language :: Python
Classifier: Natural Language :: English
Classifier: Operating System :: OS Independent
Classifier: Topic :: Internet :: WWW/HTTP
Classifier: Framework :: Zope3
